setup.py
nextbus/__init__.py
nextbus/nextbus.py
nextbus.egg-info/PKG-INFO
nextbus.egg-info/SOURCES.txt
nextbus.egg-info/dependency_links.txt
nextbus.egg-info/requires.txt
nextbus.egg-info/top_level.txt