Metadata-Version: 1.1
Name: nextbus
Version: 0.1
Summary: An API for nextbus.com
Home-page: github.com/duckworthd/nextbus
Author: Daniel Duckworth
Author-email: duckworthd@gmail.com
License: BSD
Keywords: bus data muni
Platform: UNKNOWN
Classifier: Development Status :: 4 - Beta
Classifier: License :: OSI Approved :: BSD License
Classifier: Operating System :: OS Independent
Classifier: Programming Language :: Python
